[{"__symbolic":"module","version":3,"metadata":{"FeatureComponent":{"__symbolic":"class","decorators":[{"__symbolic":"call","expression":{"__symbolic":"reference","module":"@angular/core","name":"Component"},"arguments":[{"selector":"aol-feature","template":"<ng-content></ng-content>"}]}],"members":{"id":[{"__symbolic":"property","decorators":[{"__symbolic":"call","expression":{"__symbolic":"reference","module":"@angular/core","name":"Input"}}]}],"__ctor__":[{"__symbolic":"constructor","parameters":[{"__symbolic":"reference","module":"./sources","name":"SourceVectorComponent"}]}],"ngOnInit":[{"__symbolic":"method"}],"ngOnDestroy":[{"__symbolic":"method"}],"ngOnChanges":[{"__symbolic":"method"}]}}}},{"__symbolic":"module","version":1,"metadata":{"FeatureComponent":{"__symbolic":"class","decorators":[{"__symbolic":"call","expression":{"__symbolic":"reference","module":"@angular/core","name":"Component"},"arguments":[{"selector":"aol-feature","template":"<ng-content></ng-content>"}]}],"members":{"id":[{"__symbolic":"property","decorators":[{"__symbolic":"call","expression":{"__symbolic":"reference","module":"@angular/core","name":"Input"}}]}],"__ctor__":[{"__symbolic":"constructor","parameters":[{"__symbolic":"reference","module":"./sources","name":"SourceVectorComponent"}]}],"ngOnInit":[{"__symbolic":"method"}],"ngOnDestroy":[{"__symbolic":"method"}],"ngOnChanges":[{"__symbolic":"method"}]}}}}]